mathOpp/__init__.py
mathOpp/operations.py
cmbInpaint-0.1.0.dist-info/METADATA
cmbInpaint-0.1.0.dist-info/WHEEL
cmbInpaint-0.1.0.dist-info/top_level.txt
cmbInpaint-0.1.0.dist-info/RECORD
